djangocensus/__init__.py
djangocensus/admin.py
djangocensus/apps.py
djangocensus/urls.py
djangocensus/migrations/__init__.py
djangocensus/modeladmins/CityModelAdmin.py
djangocensus/modeladmins/ContinentModelAdmin.py
djangocensus/modeladmins/CountryModelAdmin.py
djangocensus/modeladmins/DistrictModelAdmin.py
djangocensus/modeladmins/LitracyModelAdmin.py
djangocensus/modeladmins/PopulationModelAdmin.py
djangocensus/modeladmins/ReligionModelAdmin.py
djangocensus/modeladmins/ReligiousPopulationModelAdmin.py
djangocensus/modeladmins/StateModelAdmin.py
djangocensus/modeladmins/VillageModelAdmin.py
djangocensus/modeladmins/__init__.py
djangocensus/models/CityModel.py
djangocensus/models/ContinentModel.py
djangocensus/models/CountryModel.py
djangocensus/models/DistrictModel.py
djangocensus/models/LitracyModel.py
djangocensus/models/PopulationModel.py
djangocensus/models/ReligionModel.py
djangocensus/models/ReligiousPopulationModel.py
djangocensus/models/StateModel.py
djangocensus/models/VillageModel.py
djangocensus/models/__init__.py
djangocensus/rest_api/__init__.py
djangocensus/rest_api/urls.py
djangocensus/rest_api/serializers/CitySerializer.py
djangocensus/rest_api/serializers/ContinentSerializer.py
djangocensus/rest_api/serializers/CountrySerializer.py
djangocensus/rest_api/serializers/DistrictSerializer.py
djangocensus/rest_api/serializers/LitracySerializer.py
djangocensus/rest_api/serializers/PopulationSerializer.py
djangocensus/rest_api/serializers/ReligionSerializer.py
djangocensus/rest_api/serializers/ReligiousPopulationSerializer.py
djangocensus/rest_api/serializers/StateSerializer.py
djangocensus/rest_api/serializers/VillageSerializer.py
djangocensus/rest_api/serializers/__init__.py
djangocensus/rest_api/viewsets/CityCreateViewSet.py
djangocensus/rest_api/viewsets/CityDestroyViewSet.py
djangocensus/rest_api/viewsets/CityDetailViewSet.py
djangocensus/rest_api/viewsets/CityListViewSet.py
djangocensus/rest_api/viewsets/CityRetrieveUpdateViewSet.py
djangocensus-2.0.2.dist-info/License
djangocensus-2.0.2.dist-info/METADATA
djangocensus-2.0.2.dist-info/WHEEL
djangocensus-2.0.2.dist-info/top_level.txt
djangocensus-2.0.2.dist-info/RECORD
