Metadata-Version: 2.1
Name: djangocensus
Version: 2.0.2
Summary: Djangocensus: Django Reusable Census Application.
Home-page: https://github.com/bhojrampawar/djangocensus
Author: Bhojram pawar
Author-email: bhojrampawar@hotmail.com
License: MIT
Platform: UNKNOWN
Classifier: Environment :: Web Environment
Classifier: Framework :: Django
Classifier: Framework :: Django :: 2.2
Classifier: Intended Audience :: Developers
Classifier: License :: OSI Approved :: MIT License
Classifier: Operating System :: OS Independent
Classifier: Programming Language :: Python
Classifier: Programming Language :: Python :: 3.5
Classifier: Programming Language :: Python :: 3.6
Classifier: Topic :: Internet :: WWW/HTTP
Classifier: Topic :: Internet :: WWW/HTTP :: Dynamic Content
Requires-Dist: django
Requires-Dist: djangoadmin
Requires-Dist: djangotools
Requires-Dist: djangocontact
Requires-Dist: djangorestframework
